transaction_counter.py
transaction_counter_elf_unic-0.1.0.dist-info/METADATA
transaction_counter_elf_unic-0.1.0.dist-info/WHEEL
transaction_counter_elf_unic-0.1.0.dist-info/entry_points.txt
transaction_counter_elf_unic-0.1.0.dist-info/top_level.txt
transaction_counter_elf_unic-0.1.0.dist-info/RECORD
